quariadne/README.md
quariadne/__init__.py
quariadne/circuit.py
quariadne/computational_graph.py
quariadne/milp_router.py
quariadne/qiskit_passes.py
quariadne-1.0.1.dist-info/METADATA
quariadne-1.0.1.dist-info/WHEEL
quariadne-1.0.1.dist-info/entry_points.txt
quariadne-1.0.1.dist-info/RECORD
