Metadata-Version: 2.4
Name: quariadne
Version: 1.0.1
Summary: Exact solvers of the qubit routing problem
Requires-Python: >=3.13
Requires-Dist: matplotlib>=3.10.3
Requires-Dist: mypy>=1.16.0
Requires-Dist: networkx>=3.5
Requires-Dist: pydot>=4.0.1
Requires-Dist: pylatexenc>=2.10
Requires-Dist: qiskit-ibm-runtime>=0.40.1
Requires-Dist: qiskit>=2.0.1
Requires-Dist: ruff>=0.11.12
